{
  "soft_name": ["ALIEN: ISOLATION -エイリアン アイソレーション-"],
  "packages":[
    {
      "platform": "PS4",
      "company": "セガ",
      "name": "ALIEN: ISOLATION -エイリアン アイソレーション-",
      "url": "http://alienisolation.sega.jp/",
      "shop": "amazon",
      "asin": "B00UHKAVF2",
      "release_int": 20150611,
      "release_at": "2015年6月11日"
    },
    {
      "platform": "XONE",
      "company": "セガ",
      "name": "ALIEN: ISOLATION -エイリアン アイソレーション-",
      "url": "http://alienisolation.sega.jp/",
      "shop": "amazon",
      "asin": "B00UHKAVYI",
      "release_int": 20150611,
      "release_at": "2015年6月11日"
    }
  ]
}